[
  {
    "full_name": "oriolmarti97/citatBot",
    "stargazers_count": 20,
    "open_issues_count": 1,
    "forks_count": 4
  },
  {
    "full_name": "JoaquimCMH/tomeconta-tce-pe-dados",
    "stargazers_count": 3,
    "open_issues_count": 0,
    "forks_count": 0
  },
  {
    "full_name": "basujindal/stable-diffusion",
    "stargazers_count": 2292,
    "open_issues_count": 73,
    "forks_count": 324
  },
  {
    "full_name": "CompVis/stable-diffusion",
    "stargazers_count": 31798,
    "open_issues_count": 307,
    "forks_count": 4749
  },
  {
    "full_name": "axa-group/Parsr",
    "stargazers_count": 4958,
    "open_issues_count": 44,
    "forks_count": 251
  },
  {
    "full_name": "anuraghazra/github-readme-stats",
    "stargazers_count": 47369,
    "open_issues_count": 258,
    "forks_count": 11860
  },
  {
    "full_name": "cwerner/fastclass",
    "stargazers_count": 129,
    "open_issues_count": 7,
    "forks_count": 25
  },
  {
    "full_name": "nvbn/thefuck",
    "stargazers_count": 74226,
    "open_issues_count": 265,
    "forks_count": 3282
  },
  {
    "full_name": "juliasilge/supervised-ML-case-studies-course",
    "stargazers_count": 204,
    "open_issues_count": 2,
    "forks_count": 75
  },
  {
    "full_name": "spicetify/spicetify-cli",
    "stargazers_count": 12505,
    "open_issues_count": 10,
    "forks_count": 513
  },
  {
    "full_name": "MFDGaming/ubuntu-in-termux",
    "stargazers_count": 999,
    "open_issues_count": 23,
    "forks_count": 293
  },
  {
    "full_name": "smacke/ffsubsync",
    "stargazers_count": 5622,
    "open_issues_count": 53,
    "forks_count": 229
  }
]